Workbook

Sheet terms used in Excel
A1: Some terms used in Excel include:
A3: Workbook: A collection of worksheets, or spreadsheets, that make up an Excel file
A5: Worksheet: The working area of Excel, where users can store data and perform calculations
A7: Cell: The intersection of a row and a column in a table
A9: Formula: A mathematical expression that performs calculations on data in cells
A11: Filter: A function that sorts data within a file
A13: Function: A word that tells Excel what to do, such as SUM
A15: Reference: The way a formula refers to data in a cell or range of cells
A17: VLOOKUP: A function that locates specific information in cells
A19: Conditional formatting: A feature that formats cells based on certain criteria

Sheet Basic of Excel
A1: 1 | B1: EXCEL MENU SYSTEM-CALLED RIBBON | H1: 21 | I1: Move quick access tool bar below the ribbon
A2: 2 | B2: TAB | H2: 22 | I2: File is workbook and workbook is file
A3: 3 | B3: GROUP | H3: 23 | I3: workbook
A4: 4 | B4: HOME TAB-FORMAT | H4: 24 | I4: sheets tab
A5: 5 | B5: INSERT TAB-INSERTING DATA | H5: 25 | I5: column are vertical and rows are horizontal
A6: 6 | B6: DRAW TAB | H6: 26 | I6: every cell has address
A7: 7 | B7: PAGE LAYOUT TAB | H7: 27 | I7: last cell in column XFD 16384
A8: 8 | B8: Formula tab | H8: 28 | I8: last cell in rows 1048576
A9: 9 | B9: Data tab | H9: 29 | I9: formula bar-give information about active cell
A10: 10 | B10: Review tab | H10: 30 | I10: ready-this called static bar
A11: 11 | B11: Automate Tab | H11: 31 | I11: Normal view, Page layout view, Page break preview | M11: `
A12: 12 | B12: File Tab-print, save, save as | H12: 32 | I12: Zoom in and out by 10%,Fit selection
A13: 13 | B13: Dialog box launcher | H13: 33 | I13: 3D plus, cross hair , 9 way courcer
A14: 14 | B14: Ribbon Display option-tab Ctrl + Shift + F1, Ctrl+ F1 | H14: 34 | I14: Double click on navigate arrow
A15: 15 | B15: Three dots- collapse | H15: 35 | I15: Auto fill button, right click, insert row and column, cell
A16: 16 | B16: three button save, undo, redo | H16: 36 | I16: Mini tool bar
A17: 17 | B17: Ballon Tips
A18: 18 | B18: Quick access tool bar
A19: 19 | B19: add button on quick access tool bar
A20: 20 | B20: double under line
B22: alt+tab | C22: use to move from one screen to anthore screen
B23: ctrl+c | C23: copy the data
B24: ctrl+v | C24: paste the data
B25: ctrl+z | C25: go back to last step
B26: ctrl+a | C26: select entier sheet or all cells

Sheet Sheet10

Sheet Absolute and Relative cell
A1: Item | B1: Price | C1: Quantity | D1: Total Cost Formula | H1: Item | I1: Price | J1: Quantity | K1: Total Cost Formula | L1: (Tax Rate: 10%) | M1: (Tax Amount)
A2: Apple | B2: 10 | C2: 3 | D2: =B2*C2 -> 30 | E2: (Relative Cell Reference) | H2: Apple | I2: 10 | J2: 3 | K2: =I2*J2 -> 30 | L2: 0.1 | M2: =K2*$L$2 -> 3 | N2: Absolute Cell Reference
A3: Orange | B3: 15 | C3: 5 | D3: =B3*C3 -> 75 | E3: (Relative Cell Reference) | H3: Orange | I3: 15 | J3: 4 | K3: =I3*J3 -> 60 | M3: =K3*$L$2 -> 6 | N3: Absolute Cell Reference
A4: Banana | B4: 8 | C4: 5 | D4: =B4*C4 -> 40 | E4: (Relative Cell Reference) | H4: Banana | I4: 8 | J4: 5 | K4: =I4*J4 -> 40 | M4: =K4*$L$2 -> 4 | N4: Absolute Cell Reference
A6: In Excel, absolute and relative cell references determine how a formula behaves when copied to other cells. | H6: Fixed reference that does not change when copied.
A7: Default behavior in Excel. | H7: Uses $ sign before column and/or row.
A8: Changes when copied to another cell. | H8: Example: =K2+$L$2
A9: Example: =B2 + C2 | H9: Even if copied, L2 remains fixed, while K2 changes relatively.
A10: If copied from row 1 to row 2, it becomes =B3 + C3

Sheet BASIC FORMULA
A1: Count and Sum Functions
A2: COUNT | D2: COUNTIF | G2: COUNTIFS | M2: COUNTA | Q2: COUNTBLANK | U2: MAX | W2: MIN
A3: Result | D3: Result | G3: Product | H3: Qty | M3: $$$%%%&& | Q3: 45 | U3: Result | W3: Result
A4: 50 | D4: 50 | G4: Smartphone | H4: 5 | M4: 60 | Q4: 60 | U4: 50 | W4: 50
A5: Amit | D5: 60 | G5: Laptop | H5: 6 | M5: ,,,,,,, | Q5: apple | U5: 60 | W5: 60
A6: 80 | D6: 80 | G6: Smartphone | H6: 4 | M6: banana | Q6: banana | U6: 80 | W6: 80
A7: 90 | D7: 90 | G7: Laptop | H7: 2 | M7: 100 | N7: =COUNTA(M3:M8) -> 6 | Q7: 100 | U7: 90 | W7: 90
A8: 70 | D8: 70 | G8: Smartphone | H8: 1 | M8: orange | Q8: orange | U8: 70 | W8: 70
A9: 90 | D9: 90 | H9: =COUNTIFS(G4:G8,"Laptop",H4:H8,">4") -> 1 | I9: =COUNTIFS(G4:G8,"smartphone",H4:H8,">4") -> 1 | M9: =COUNTA(M3:M8) -> 6 | N9: COUNTA(M3:M8) | U9: 90 | W9: 90
A10: =COUNT(A4:A9) -> 5 | B10: =COUNT(A4:A9) -> 5 | D10: =COUNTIF(D4:D9,">60") -> 4 | E10: =COUNTIF(D4:D9,">70") -> 3 | G10: COUNTIFS(G4:G8,"Laptop",H4:H8,">4") | M10: =COUNT(M3:M8) -> 2 | N10: COUNT(A4:A9) | Q10: 75 | U10: =MAX(U4:U9) -> 90 | W10: =MIN(W4:W9) -> 50
A11: COUNT(A4:A9) | D11: COUNTIF(D4:D9,">60") | Q11: GRAPES | R11: =COUNTBLANK(Q3:Q13) -> 2
A13: SUM | D13: SUMIF | G13: SUMIFS | N13: Average | Q13: 200
A14: Result | D14: Result | G14: Product | H14: Company | I14: Qty | K14: smartphone | L14: Samsung | N14: profit | Q14: =COUNTBLANK(Q3:Q13) -> 2 | R14: COUNTBLANK(Q3:Q13)
A15: 50 | D15: 50 | G15: Smartphone | H15: Samsung | I15: 5 | N15: 50 | Q15: =COUNTA(Q3:Q13) -> 9
A16: 60 | D16: 60 | G16: Laptop | H16: HP | I16: 6 | N16: 60
A17: 70 | D17: 70 | G17: Smartphone | H17: HP | I17: 4 | K17: =SUMIFS(I15:I19,G15:G19,K14,H15:H19,L14) -> 10 | N17: 70
A18: 90 | D18: 90 | G18: Laptop | H18: Samsung | I18: 2 | N18: 90
A19: =SUM(A15:A18) -> 270 | D19: =SUMIF(D15:D18,">60") -> 160 | G19: Smartphone | H19: Samsung | I19: 5 | N19: =AVERAGE(N15:N18) -> 67.5
A20: SUM(A15:A20) | D20: SUMIF(D15:D18,">60") | I20: =SUMIFS(I15:I19,G15:G19,"Smartphone",H15:H19,"Samsung") -> 10 | J20: =SUMIFS(I15:I19,G15:G19,G15,H15:H19,H15) -> 10
A22: =SUM(A15:A18) -> 270 | D22: =SUMIF(D15:D18,">60") -> 160 | G22: SUMIFS(I15:I19,G15:G19,"Smartphone",H15:H19,"Samsung")

Sheet VLookup funtion
A1: VLOOKUP function
A2: Score | B2: Grade | G2: ID | H2: First Name | I2: Last Name | J2: Salary | O2: Employee ID | P2: Name | Q2: Department | R2: Salary | S2: Location | T2: Joining Date
A3: 30 | B3: F | D3: Score | E3: 88 | G3: 1 | H3: Ram | I3: Kumar | J3: 30000 | L3: First Name | M3: 4 | O3: 101 | P3: Raj | Q3: IT | R3: 60000 | S3: =VLOOKUP(O3,HLOOKUP!A2:C7,3,0) -> Mumbai | T3: =VLOOKUP(O3,HLOOKUP!A2:C7,2,0) -> 43842 | V3: VLOOKUP(O3,HLOOKUP!A2:C7,3,0)
A4: 60.5 | B4: D | D4: Grade | E4: =VLOOKUP(E3,A2:B7,2,FALSE) -> A | G4: 2 | H4: Sumit | I4: Sharma | J4: 40000 | L4: Salary | M4: =VLOOKUP(M3,G2:J9,4,0) -> 80000 | O4: 102 | P4: Simran | Q4: HR | R4: 55000 | S4: =VLOOKUP(O4,HLOOKUP!A3:C8,3,0) -> Delhi | T4: =VLOOKUP(O4,HLOOKUP!A3:C8,2,0) -> 43529
A5: 85 | B5: B+ | G5: 3 | H5: Pooja | I5: Mishra | J5: 50000 | O5: 103 | P5: Amit | Q5: Finance | R5: 70000 | S5: =VLOOKUP(O5,HLOOKUP!A4:C9,3,0) -> Bangalore | T5: =VLOOKUP(O5,HLOOKUP!A4:C9,2,0) -> 44395 | V5: VLOOKUP(O3,HLOOKUP!A2:C7,2,0)
A6: 88 | B6: A | G6: 4 | H6: Mohan | I6: Singh | J6: 80000 | O6: 104 | P6: Neha | Q6: IT | R6: 65000 | S6: =VLOOKUP(O6,HLOOKUP!A5:C10,3,0) -> Chennai | T6: =VLOOKUP(O6,HLOOKUP!A5:C10,2,0) -> 44096
A7: 70 | B7: C | G7: 5 | H7: Diya | I7: Kumari | J7: 45000 | L7: VLOOKUP(M3,G2:J9,4,0) | O7: 105 | P7: Arjun | Q7: Marketing | R7: 62000 | S7: =VLOOKUP(O7,HLOOKUP!A6:C11,3,0) -> Kolkata | T7: =VLOOKUP(O7,HLOOKUP!A6:C11,2,0) -> 43414
D8: Score | E8: 85 | G8: 6 | H8: Rohit | I8: Dutta | J8: 42000
D9: Grade | E9: =VLOOKUP(E8,A3:B7,2,TRUE) -> B+ | G9: 7 | H9: Chetan | I9: Bugha | J9: 60000
O10: 102 | P10: Simran | Q10: HR | R10: 55000 | S10: =VLOOKUP(O10,HLOOKUP!$A$2:$C$7,3,0) -> Delhi
B11: VLOOKUP(E3,A2:B7,2,FALSE) | O11: 104 | P11: Neha | Q11: IT | R11: 65000 | S11: =VLOOKUP(O11,HLOOKUP!$A$2:$C$7,3,0) -> Chennai
O12: 101 | P12: Raj | Q12: IT | R12: 60000 | S12: =VLOOKUP(O12,HLOOKUP!$A$2:$C$7,3,0) -> Mumbai

Sheet HLOOKUP
E1: HLOOKUP (Horizontal lookup) function. | P1: MATCH function | V1: INDEX function
A2: Employee ID | B2: Joining Date | C2: Location | E2: ID | F2: Product | V2: two-dimensional range.
A3: 101 | B3: 43842 | C3: Mumbai | E3: 111 | F3: =HLOOKUP(E3,$I$5:$N$7,3,0) -> Laptop | R3: Product | V3: 2 | W3: 2 | X3: {=INDEX(Y6:AA10,V3,W3)} -> 2000 | Z3: INDEX(Y6:AA10,V3,W3)
A4: 102 | B4: 43529 | C4: Delhi | E4: 222 | F4: =HLOOKUP(E4,$I$5:$N$7,3,0) -> Keyboard | P4: banana | R4: APPLE
A5: 103 | B5: 44395 | C5: Bangalore | E5: 333 | F5: =HLOOKUP(E5,$I$5:$N$7,3,0) -> Mouse | I5: ID | J5: 111 | K5: 222 | L5: 333 | M5: 777 | N5: 888 | P5: =MATCH(P4,R3:R7,0) -> 4 | R5: ORANGE
A6: 104 | B6: 44096 | C6: Chennai | E6: 111 | F6: =HLOOKUP(E6,$I$5:$N$7,3,0) -> Laptop | I6: Brand | J6: HP | K6: DELL | L6: INTEL | M6: HP | N6: Logitech | R6: BANANA | Y6: 450 | Z6: 1000 | AA6: 5
A7: 105 | B7: 43414 | C7: Kolkata | E7: 222 | F7: =HLOOKUP(E7,$I$5:$N$7,3,0) -> Keyboard | I7: Product | J7: Laptop | K7: Keyboard | L7: Mouse | M7: DVD | N7: Printer | R7: PAPAYA | U7: INDEX(Y12:Y15,V12) | Y7: 100 | Z7: 2000 | AA7: 2
E8: 888 | F8: =HLOOKUP(E8,$I$5:$N$7,3,0) -> Printer | Y8: 500 | Z8: 3000 | AA8: 6
E9: 777 | F9: =HLOOKUP(E9,$I$5:$N$7,3,0) -> DVD | P9: MATCH(P4,R4:R7,0) | Y9: 800 | Z9: 4000 | AA9: 8
Y10: 900 | Z10: 5000 | AA10: 9
E11: HLOOKUP(E3,$J$5:$N$7,3,FALSE) | V11: one-dimensional range
V12: 4 | W12: {=INDEX(Y12:Y15,V12)} -> 80 | Y12: 50
P13: returns the position of a value in a given range. | V13: 3 | Y13: 60
Y14: 70
Y15: 80
W17: Returns a value from a specified table or range based on the given row and column number.

Sheet Nested VLOOKUP
A1: Nested VLOOKUP | L1: INDEX and MATCH
A2: Employee ID | B2: Employee Name | C2: Department | E2: Department | F2: Manager | M2: D (Salary) | N2: A (ID) | O2: B (Name) | P2: C (Salary)
A3: 101 | B3: John | C3: IT | E3: IT | F3: Mr. Sharma | M3: 100 | N3: 101 | O3: John | P3: 50000
A4: 102 | B4: Alice | C4: HR | E4: HR | F4: Ms. Kapoor | M4: 500 | N4: 102 | O4: Mike | P4: 60000
A5: 103 | B5: Mark | C5: Finance | E5: Finance | F5: Mr. Verma | M5: 600 | N5: 103 | O5: Sara | P5: 70000
A6: 104 | B6: Sarah | C6: IT
A7: 105 | B7: Emma | C7: HR
M8: ID | N8: 102 | O8: 101 | P8: 103
M9: SALARY | N9: =INDEX(M3:M5,MATCH($N$8,$N$3:$N$5,0)) -> 500 | O9: =INDEX(N3:N5,MATCH($N$8,$N$3:$N$5,0)) -> 102 | P9: =INDEX(O3:O5,MATCH($N$8,$N$3:$N$5,0)) -> Mike
A10: 101 | B10: =VLOOKUP(VLOOKUP(A10,A2:C8,3,0),$E$2:$F$7,2,0) -> Mr. Sharma
A11: 102 | B11: =VLOOKUP(VLOOKUP(A11,A3:C9,3,0),$E$2:$F$7,2,0) -> Ms. Kapoor
A12: 103 | B12: =VLOOKUP(VLOOKUP(A12,A4:C10,3,0),$E$2:$F$7,2,0) -> Mr. Verma | D12: VLOOKUP(VLOOKUP(A9,$A$2:$C$6,3,FALSE),$E$2:$F$6,2,FALSE) | M12: INDEX(M3:M5,MATCH(N8,N3:N5,0))
A13: 104 | B13: =VLOOKUP(VLOOKUP(A13,A5:C11,3,0),$E$2:$F$7,2,0) -> Mr. Sharma
A14: 105 | B14: =VLOOKUP(VLOOKUP(A14,A6:C12,3,0),$E$2:$F$7,2,0) -> Ms. Kapoor
I16: INDEX(M3:M5,MATCH(N8,N3:N5,0))
